dict_collection
