Metadata-Version: 2.1
Name: dict-collection
Version: 1.0.5
Summary: Utility data structure
Author: spwn02
Author-email: spwn.contact@gmail.com
Keywords: dict_collection,dict,collection,dict,spwn02
Classifier: Development Status :: 4 - Beta
Classifier: Intended Audience :: Developers
Classifier: Programming Language :: Python :: 3
Classifier: License :: OSI Approved :: MIT License
Classifier: Operating System :: OS Independent
Requires-Python: >=3.6
